memly/__init__.py
memly/_version.py
memly/analysis.py
memly/countlipids.py
memly/loader.py
memly/membrane.py
memly/memly.py
memly/metrics.py
memly/orderparam.py
memly/particle_naming.py
memly/sa_analyses.py
memly/thickness.py
memly/data/README.md
memly/data/look_and_say.dat
memly/tests/__init__.py
memly/tests/test_00_single_frame.py
memly/tests/test_01_trajectory.py
memly/tests/test_02_trajectory.py
memly/tests/test_03_point_cloud_normals.py
memly/tests/test_04_sa_analyses.py
memly/tests/test_05_countlipids.py
memly/tests/test_06_order_parameter.py
memly/tests/test_07_thickness.py
memly/tests/test_complete_workflow.py
memly/tests/test_highly_curved_surface.py
memly/tests/test_memly.py
memly/tests/test_vector_angle.py
memly/tests/data/1.pdb
memly/tests/data/1.xtc
memly/tests/data/2.pdb
memly/tests/data/2.xtc
memly/tests/data/2_old.pdb
memly/tests/data/2_old.xtc
memly/tests/data/cube_twist.obj
memly/tests/data/labelled.pdb
memly/tests/data/labelled_converted.pdb
memly/tests/data/normals.pdb
memly/tests/data/normals_converted.pdb
memly/tests/data/point_cloud.obj
memly/tests/data/simulation_data_source.note
memly/tests/data/snap.pdb
memly/tests/data/leaflet_id/0.pdb
memly/tests/data/leaflet_id/0_converted.pdb
memly/tests/data/leaflet_id/1.pdb
memly/tests/data/leaflet_id/10.pdb
memly/tests/data/leaflet_id/10_converted.pdb
memly/tests/data/leaflet_id/11.pdb
memly/tests/data/leaflet_id/11_converted.pdb
memly/tests/data/leaflet_id/12.pdb
memly/tests/data/leaflet_id/12_converted.pdb
memly/tests/data/leaflet_id/13.pdb
memly/tests/data/leaflet_id/13_converted.pdb
memly/tests/data/leaflet_id/14.pdb
memly/tests/data/leaflet_id/14_converted.pdb
memly/tests/data/leaflet_id/15.pdb
memly/tests/data/leaflet_id/15_converted.pdb
memly/tests/data/leaflet_id/16.pdb
memly/tests/data/leaflet_id/16_converted.pdb
memly/tests/data/leaflet_id/17.pdb
memly/tests/data/leaflet_id/17_converted.pdb
memly/tests/data/leaflet_id/18.pdb
memly/tests/data/leaflet_id/18_converted.pdb
memly-0.1.1.dist-info/LICENSE
memly-0.1.1.dist-info/METADATA
memly-0.1.1.dist-info/WHEEL
memly-0.1.1.dist-info/top_level.txt
memly-0.1.1.dist-info/RECORD
