Metadata-Version: 2.1
Name: memly
Version: 0.1.1
Summary: UNKNOWN
Home-page: https://github.com/tamir-dingjan/memly
Author: Tamir Dingjan
Author-email: tamir.dingjan@gmail.com
License: MIT
Platform: UNKNOWN
